lean_lsp_mcp/__init__.py
lean_lsp_mcp/__main__.py
lean_lsp_mcp/client_utils.py
lean_lsp_mcp/file_utils.py
lean_lsp_mcp/instructions.py
lean_lsp_mcp/loogle.py
lean_lsp_mcp/models.py
lean_lsp_mcp/outline_utils.py
lean_lsp_mcp/profile_utils.py
lean_lsp_mcp/search_utils.py
lean_lsp_mcp/server.py
lean_lsp_mcp/utils.py
lean_lsp_mcp-0.19.2.dist-info/licenses/LICENSE
lean_lsp_mcp-0.19.2.dist-info/METADATA
lean_lsp_mcp-0.19.2.dist-info/WHEEL
lean_lsp_mcp-0.19.2.dist-info/entry_points.txt
lean_lsp_mcp-0.19.2.dist-info/top_level.txt
lean_lsp_mcp-0.19.2.dist-info/RECORD
