Metadata-Version: 2.4
Name: lean-lsp-mcp
Version: 0.19.2
Summary: Lean Theorem Prover MCP
Author-email: Oliver Dressler <hey@oli.show>
License-Expression: MIT
Project-URL: Repository, https://github.com/oOo0oOo/lean-lsp-mcp
Requires-Python: >=3.10
License-File: LICENSE
Requires-Dist: leanclient==0.9.2
Requires-Dist: mcp[cli]==1.25.0
Requires-Dist: orjson>=3.11.1
Requires-Dist: certifi>=2024.0.0
Provides-Extra: lint
Requires-Dist: ruff>=0.2.0; extra == "lint"
Provides-Extra: dev
Requires-Dist: ruff>=0.2.0; extra == "dev"
Requires-Dist: pytest>=8.3; extra == "dev"
Requires-Dist: anyio>=4.4; extra == "dev"
Requires-Dist: pytest-asyncio>=0.23; extra == "dev"
Requires-Dist: pytest-timeout>=2.3; extra == "dev"
Dynamic: license-file
